MANIFEST.in
README.txt
setup.py
atreal/__init__.py
atreal/__init__.pyc
atreal.richfile.preview.egg-info/PKG-INFO
atreal.richfile.preview.egg-info/SOURCES.txt
atreal.richfile.preview.egg-info/dependency_links.txt
atreal.richfile.preview.egg-info/entry_points.txt
atreal.richfile.preview.egg-info/namespace_packages.txt
atreal.richfile.preview.egg-info/not-zip-safe
atreal.richfile.preview.egg-info/requires.txt
atreal.richfile.preview.egg-info/top_level.txt
atreal/richfile/__init__.py
atreal/richfile/__init__.pyc
atreal/richfile/preview/__init__.py
atreal/richfile/preview/adapters.py
atreal/richfile/preview/configure.zcml
atreal/richfile/preview/events.py
atreal/richfile/preview/interfaces.py
atreal/richfile/preview/tests.py
atreal/richfile/preview/upgrades.py
atreal/richfile/preview/version.txt
atreal/richfile/preview/browser/__init__.py
atreal/richfile/preview/browser/configure.zcml
atreal/richfile/preview/browser/controlpanel.pt
atreal/richfile/preview/browser/controlpanel.py
atreal/richfile/preview/browser/preview.kss
atreal/richfile/preview/browser/richfilepreview_icon.png
atreal/richfile/preview/browser/view.pt
atreal/richfile/preview/browser/viewlet.pt
atreal/richfile/preview/browser/viewlets.py
atreal/richfile/preview/browser/views.py
atreal/richfile/preview/locales/atreal.richfile.preview.pot
atreal/richfile/preview/locales/fr/LC_MESSAGES/atreal.richfile.preview.po
atreal/richfile/preview/profiles/default/actionicons.xml
atreal/richfile/preview/profiles/default/browserlayer.xml
atreal/richfile/preview/profiles/default/componentregistry.xml
atreal/richfile/preview/profiles/default/controlpanel.xml
atreal/richfile/preview/profiles/default/kssregistry.xml
atreal/richfile/preview/profiles/default/metadata.xml
docs/HISTORY.txt
docs/INSTALL.txt
docs/LICENSE.GPL
docs/LICENSE.txt