Metadata-Version: 1.0
Name: atreal.richfile.preview
Version: 0.2.0
Summary: Preview Support Plugin for RichFileQualifier
Home-page: http://svn.plone.org/svn/collective/atreal.richfile.preview/
Author: atReal
Author-email: contact@atreal.fr
License: GPL
Keywords: richfile plone preview atreal
Platform: UNKNOWN
Classifier: Framework :: Plone
Classifier: Programming Language :: Python
